{
  "id": "Dans le ring",
  "collectionCardId": "stadium",
  "cost": 0,
  "xCost": false,
  "type": "Compétence",
  "rarity": "Common",
  "targetingMode": "Enemy",
  "exhaust": false,
  "retain": false,
  "effects": [
    {
      "type": "Armor",
      "value": 6,
      "targetSelf": true,
      "targetOthers": false,
      "statusType": "Strength",
      "duration": 0,
      "description": "",
      "cardID": "",
      "conditional": false,
      "conditionType": "KillingBlow",
      "conditionValue": null,
      "trueEffect": false
    },
    {
      "type": "Status",
      "value": 0,
      "targetSelf": false,
      "targetOthers": false,
      "statusType": "Weakness",
      "duration": 1,
      "description": "",
      "cardID": "",
      "conditional": false,
      "conditionType": "KillingBlow",
      "conditionValue": null,
      "trueEffect": false
    }
  ],
  "modifiers": [],
  "favoredCharacter": "Aucun",
  "animationSpeed": 1.0,
  "innate": false,
  "startingCount": 0
}