{
  "id": "Smash",
  "collectionCardId": "toss",
  "cost": 3,
  "xCost": false,
  "type": "Attaque",
  "rarity": "Rare",
  "targetingMode": "Enemy",
  "exhaust": false,
  "retain": false,
  "effects": [
    {
      "type": "Damage",
      "value": 27,
      "targetSelf": false,
      "targetOthers": false,
      "statusType": "Strength",
      "duration": 0,
      "description": "",
      "cardID": null,
      "conditional": false,
      "conditionType": "KillingBlow",
      "conditionValue": null,
      "trueEffect": false
    }
  ],
  "modifiers": [],
  "favoredCharacter": "Aucun",
  "animationSpeed": 1.0,
  "innate": false,
  "startingCount": 0
}